odoo/addons/repair_refurbish/README.rst
odoo/addons/repair_refurbish/__init__.py
odoo/addons/repair_refurbish/__manifest__.py
odoo/addons/repair_refurbish/data/stock_data.xml
odoo/addons/repair_refurbish/i18n/de.po
odoo/addons/repair_refurbish/i18n/it.po
odoo/addons/repair_refurbish/i18n/mrp_repair_refurbish.pot
odoo/addons/repair_refurbish/i18n/repair_refurbish.pot
odoo/addons/repair_refurbish/models/__init__.py
odoo/addons/repair_refurbish/models/product_product.py
odoo/addons/repair_refurbish/models/product_template.py
odoo/addons/repair_refurbish/models/repair.py
odoo/addons/repair_refurbish/models/stock_move.py
odoo/addons/repair_refurbish/readme/CONFIGURE.md
odoo/addons/repair_refurbish/readme/CONTRIBUTORS.md
odoo/addons/repair_refurbish/readme/CREDITS.md
odoo/addons/repair_refurbish/readme/DESCRIPTION.md
odoo/addons/repair_refurbish/readme/USAGE.md
odoo/addons/repair_refurbish/static/description/icon.png
odoo/addons/repair_refurbish/static/description/index.html
odoo/addons/repair_refurbish/tests/__init__.py
odoo/addons/repair_refurbish/tests/test_repair_refurbish.py
odoo/addons/repair_refurbish/views/product_product_view.xml
odoo/addons/repair_refurbish/views/product_template_view.xml
odoo/addons/repair_refurbish/views/repair_view.xml
odoo_addon_repair_refurbish-17.0.2.0.0.3.dist-info/METADATA
odoo_addon_repair_refurbish-17.0.2.0.0.3.dist-info/WHEEL
odoo_addon_repair_refurbish-17.0.2.0.0.3.dist-info/top_level.txt
odoo_addon_repair_refurbish-17.0.2.0.0.3.dist-info/RECORD
